{
  "main": {
    "id": "954a96b2c103c5c5",
    "type": "split",
    "children": [
      {
        "id": "c68022702e445f05",
        "type": "tabs",
        "children": [
          {
            "id": "0ae74d31ad1b1e8b",
            "type": "leaf",
            "state": {
              "type": "release-notes",
              "state": {
                "currentVersion": "1.11.7"
              },
              "icon": "lucide-book-up",
              "title": "Release Notes 1.11.7"
            }
          }
        ]
      }
    ],
    "direction": "vertical"
  },
  "left": {
    "id": "0da2675289d8c748",
    "type": "split",
    "children": [
      {
        "id": "503a27c1b589e654",
        "type": "tabs",
        "children": [
          {
            "id": "35673f571d6f2eae",
            "type": "leaf",
            "state": {
              "type": "file-explorer",
              "state": {
                "sortOrder": "alphabetical",
                "autoReveal": false
              },
              "icon": "lucide-folder-closed",
              "title": "Files"
            }
          },
          {
            "id": "592ac87e2e76c383",
            "type": "leaf",
            "state": {
              "type": "search",
              "state": {
                "query": "",
                "matchingCase": false,
                "explainSearch": false,
                "collapseAll": false,
                "extraContext": false,
                "sortOrder": "alphabetical"
              },
              "icon": "lucide-search",
              "title": "Search"
            }
          },
          {
            "id": "66e7f883febab277",
            "type": "leaf",
            "state": {
              "type": "bookmarks",
              "state": {},
              "icon": "lucide-bookmark",
              "title": "Bookmarks"
            }
          }
        ]
      }
    ],
    "direction": "horizontal",
    "width": 300
  },
  "right": {
    "id": "6dd6586be2093e5d",
    "type": "split",
    "children": [
      {
        "id": "92e5a75775f914d3",
        "type": "tabs",
        "children": [
          {
            "id": "70ed2d8e8bed1539",
            "type": "leaf",
            "state": {
              "type": "backlink",
              "state": {
                "file": "EE foundation/Parallel and series Resistance(TODO).md",
                "collapseAll": false,
                "extraContext": false,
                "sortOrder": "alphabetical",
                "showSearch": false,
                "searchQuery": "",
                "backlinkCollapsed": false,
                "unlinkedCollapsed": true
              },
              "icon": "links-coming-in",
              "title": "Backlinks for Parallel and series Resistance(TODO)"
            }
          },
          {
            "id": "530e48f4f9c4da15",
            "type": "leaf",
            "state": {
              "type": "outgoing-link",
              "state": {
                "file": "EE foundation/Parallel and series Resistance(TODO).md",
                "linksCollapsed": false,
                "unlinkedCollapsed": true
              },
              "icon": "links-going-out",
              "title": "Outgoing links from Parallel and series Resistance(TODO)"
            }
          },
          {
            "id": "67cd3c93fb1986cd",
            "type": "leaf",
            "state": {
              "type": "tag",
              "state": {
                "sortOrder": "frequency",
                "useHierarchy": true,
                "showSearch": false,
                "searchQuery": ""
              },
              "icon": "lucide-tags",
              "title": "Tags"
            }
          },
          {
            "id": "cfcb4f5907007ecb",
            "type": "leaf",
            "state": {
              "type": "outline",
              "state": {
                "file": "EE foundation/Parallel and series Resistance(TODO).md",
                "followCursor": false,
                "showSearch": false,
                "searchQuery": ""
              },
              "icon": "lucide-list",
              "title": "Outline of Parallel and series Resistance(TODO)"
            }
          },
          {
            "id": "a03f84f6d2f6444f",
            "type": "leaf",
            "state": {
              "type": "git-view",
              "state": {},
              "icon": "git-pull-request",
              "title": "Source Control"
            }
          }
        ],
        "currentTab": 4
      }
    ],
    "direction": "horizontal",
    "width": 300
  },
  "left-ribbon": {
    "hiddenItems": {
      "bases:Create new base": false,
      "switcher:Open quick switcher": false,
      "graph:Open graph view": false,
      "canvas:Create new canvas": false,
      "daily-notes:Open today's daily note": false,
      "templates:Insert template": false,
      "command-palette:Open command palette": false,
      "obsidian-git:Open Git source control": false
    }
  },
  "active": "35673f571d6f2eae",
  "lastOpenFiles": [
    "Untitled.base",
    "unorganized stuff/Questions.md",
    "unorganized stuff/answers.md",
    "unorganized stuff/Priority encoder truth table(need a folder to store image).png",
    "unorganized stuff/output code TODO.md",
    "unorganized stuff/Flyback diode on dc motor.png",
    "unorganized stuff/flyback diode.md",
    "Untitled 1.base",
    "Untitled.canvas",
    "FPGA/Finite State Machine(FSM).md",
    "FPGA/photos/Finite State Machine.png",
    "FPGA/photos/Timing Diagram.png",
    "FPGA/LUT.md",
    "FPGA/HDL.md",
    "FPGA/FPGA VS ASIC VS microcontrollers.md",
    "FPGA/Flip-Flop.md",
    "FPGA/buffer.md",
    "FPGA/black box.md",
    "FPGA/Untitled.canvas",
    "FPGA/photos/Black box.png",
    "FPGA/photos",
    "FPGA/photos/LUT.png",
    "FPGA/photos/AND GATE.png",
    "FPGA",
    "unorganized stuff/Untitled.base",
    "unorganized stuff",
    "EE foundation/transistors/CMOS/transconductance.md",
    "EE foundation/transistors/CMOS/images/Behavior of transconductance.png",
    "EE foundation/transistors/CMOS/images/transconductance equation.png",
    "EE foundation/transistors/CMOS/MOSFET regions.md",
    "EE foundation/transistors/CMOS/overdrive voltage.md",
    "EE foundation/transistors/BJT(TODO).md",
    "EE foundation/transistors/CMOS/source.md",
    "EE foundation/transistors/CMOS/Threshold voltage.md",
    "EE foundation/transistors/CMOS/images/Mosfet regions visualization.png",
    "EE foundation/transistors/CMOS/MOSFET structure.md",
    "EE foundation/differential input.md",
    "EE foundation/transistors/CMOS/aspect ratio.md",
    "analog hardware engineer/Data Converters/Nyquist theorem and Anti-aliasing filters (TODO).md",
    "analog hardware engineer/Data Converters/Fan Folding.md",
    "analog hardware engineer/amplifiers/common emitter(TODO).md",
    "analog hardware engineer/amplifiers/Common collector(TODO).md",
    "Untitled 2.base",
    "EE foundation/transistors/CMOS/body.md",
    "EE foundation/transistors",
    "EE foundation/CMOS/Untitled",
    "EE foundation/transistors/CMOS/images"
  ]
}